datalake_catalog/__init__.py
datalake_catalog/api.py
datalake_catalog/app.py
datalake_catalog/config/default.json
datalake_catalog/main.py
datalake_catalog/model.py
datalake_catalog/schemas/__init__.py
datalake_catalog/schemas/catalog.json
datalake_catalog/schemas/configuration.json
datalake_catalog/schemas/storage.json
datalake_catalog/security.py
datalake_catalog/settings.py
datalake_catalog-1.0.4.dist-info/entry_points.txt
datalake_catalog-1.0.4.dist-info/LICENSE
datalake_catalog-1.0.4.dist-info/WHEEL
datalake_catalog-1.0.4.dist-info/METADATA
datalake_catalog-1.0.4.dist-info/RECORD
