Metadata-Version: 2.1
Name: datalake-catalog
Version: 1.0.4
Summary: Datalake Catalog
Home-page: https://github.com/equancy/datalake-catalog
License: MIT
Author: Didier SCHMITT
Author-email: dschmitt@equancy.com
Requires-Python: >=3.8,<4.0
Classifier: Development Status :: 4 - Beta
Classifier: License :: OSI Approved :: MIT License
Classifier: Programming Language :: Python :: 3
Classifier: Programming Language :: Python :: 3.10
Classifier: Programming Language :: Python :: 3.8
Classifier: Programming Language :: Python :: 3.9
Classifier: Topic :: Internet :: WWW/HTTP :: WSGI :: Application
Provides-Extra: all
Provides-Extra: mysql
Provides-Extra: pgsql
Requires-Dist: Flask (>=2.1.2,<3.0.0)
Requires-Dist: Flask-JWT-Extended (>=4.4.0,<5.0.0)
Requires-Dist: PyMySQL (>=1.0.2,<2.0.0); extra == "all" or extra == "mysql"
Requires-Dist: click (>=8.1.3,<9.0.0)
Requires-Dist: gunicorn (>=20.1.0,<21.0.0)
Requires-Dist: jsonschema (>=4.5.1,<5.0.0)
Requires-Dist: pony (==0.7.16)
Requires-Dist: psycopg2-binary (>=2.9.3,<3.0.0); extra == "all" or extra == "pgsql"
Project-URL: Repository, https://github.com/equancy/datalake-catalog
